chromiumfile/__init__.py
chromiumfile/_core.py
chromiumfile/test.py
chromiumfile/licenses/README.md
chromiumfile/licenses/chromium/LICENSE
chromiumfile-0.2.dist-info/LICENSE
chromiumfile-0.2.dist-info/WHEEL
chromiumfile-0.2.dist-info/METADATA
chromiumfile-0.2.dist-info/RECORD
