Metadata-Version: 2.1
Name: chromiumfile
Version: 0.2
Summary: chromium 浏览器的文件镜像
Keywords: chromiumfile,chromium,chrome
Author-email: "lcctoor.com" <lcctoor@outlook.com>
Classifier: License :: OSI Approved :: Apache Software License
Project-URL: HomePage, https://github.com/lcctoor/arts
